{
  "data": [
    {
      "channelId": "UCDoKpv2rC6SYE_9ZurfBYbQ",
      "name": "きのこ",
      "timeSec": 1329
    },
    {
      "channelId": "UC6dzpfLDOZpgLEbD6RjR-oQ",
      "name": "がんばろ",
      "timeSec": 2553
    },
    {
      "channelId": "UCDV95uUZlqOmxJ0hONnoALw",
      "name": "小倉あん",
      "timeSec": 30000
    },
    {
      "channelId": "UCkBSZ6a0qW_X_jjPhekzDwQ",
      "name": "ゆきぽ",
      "timeSec": 23386
    },
    {
      "channelId": "UCK8iaQPBs9qYFyzjPye5CEg",
      "name": "篠岡えりの日常(Eri Shinoka)",
      "timeSec": 26677
    },
    {
      "channelId": "UCIsZNFLIooBrdnqzg7R37qg",
      "name": "ぐぅぐぅ",
      "timeSec": 23668
    },
    {
      "channelId": "UCJeqXqAFicpGzWZbG0nVU6A",
      "name": "いかす",
      "timeSec": 19753
    },
    {
      "channelId": "UCd6QtfSvwrB3JJlfbE1WiKg",
      "name": "ちぃ",
      "timeSec": 15705
    },
    {
      "channelId": "UC6HPl7foTp2UZAZWPVC7bsw",
      "name": "ごま",
      "timeSec": 19334
    }
  ]
}