{
  "data": [
    {
      "channelId": "UCDV95uUZlqOmxJ0hONnoALw",
      "name": "小倉あん",
      "timeSec": 30360
    },
    {
      "channelId": "UCXdQBFuo2lM1Q7zOPQf-Wdg",
      "name": "アップルπ314",
      "timeSec": 17596
    },
    {
      "channelId": "UC6dzpfLDOZpgLEbD6RjR-oQ",
      "name": "がんばろ",
      "timeSec": 3207
    },
    {
      "channelId": "UCK8iaQPBs9qYFyzjPye5CEg",
      "name": "篠岡えりの日常(Eri Shinoka)",
      "timeSec": 8429
    },
    {
      "channelId": "UCkBSZ6a0qW_X_jjPhekzDwQ",
      "name": "ゆきぽ",
      "timeSec": 12086
    },
    {
      "channelId": "UCEgzo1yNYRKm6HkuroYl4xw",
      "name": "おしるこポタージュ",
      "timeSec": 17439
    },
    {
      "channelId": "UCJeqXqAFicpGzWZbG0nVU6A",
      "name": "いかす",
      "timeSec": 27005
    },
    {
      "channelId": "UCd6QtfSvwrB3JJlfbE1WiKg",
      "name": "ちぃ",
      "timeSec": 25520
    },
    {
      "channelId": "UCuFQ6AcqOX5vgE30JanOlcg",
      "name": "ぱるぱる",
      "timeSec": 3196
    },
    {
      "channelId": "UC-6QFs2WaX1u5E3zFOIbbHg",
      "name": "Eri",
      "timeSec": 3462
    },
    {
      "channelId": "UCMGarxOhOmQQjf045tsNCIw",
      "name": "だからからだ-p8b",
      "timeSec": 6765
    },
    {
      "channelId": "UCuE5Lp-fd5e20RcLLUhOy0Q",
      "name": "okopure0310",
      "timeSec": 11903
    },
    {
      "channelId": "UC35lCaPB9LnhD6mmPXbYQRA",
      "name": "あやもこぷー",
      "timeSec": 10275
    },
    {
      "channelId": "UC3NSHthaQHhHxYIpMwYcS_Q",
      "name": "kosu807",
      "timeSec": 9872
    },
    {
      "channelId": "UCOHBR-86O5EfmHP9qoAyAGQ",
      "name": "もんぶらんYouTube",
      "timeSec": 6257
    },
    {
      "channelId": "UCMsxPbR_g7semb56kcwKzgg",
      "name": "yuyuyuyuuyyuuyuuy",
      "timeSec": 23787
    }
  ]
}