{
  "data": [
    {
      "channelId": "UCDTWKvGJ1sDOlYHGYtAR7EQ",
      "name": "琴音 倉内",
      "timeSec": 22743
    },
    {
      "channelId": "UCDV95uUZlqOmxJ0hONnoALw",
      "name": "小倉あん",
      "timeSec": 26945
    },
    {
      "channelId": "UCIsZNFLIooBrdnqzg7R37qg",
      "name": "ぐぅぐぅ",
      "timeSec": 27016
    },
    {
      "channelId": "UCdsHgUWtZ7t55pj3YWi0VoQ",
      "name": "tohu",
      "timeSec": 15259
    },
    {
      "channelId": "UCkBSZ6a0qW_X_jjPhekzDwQ",
      "name": "ゆきぽ",
      "timeSec": 22070
    },
    {
      "channelId": "UC_YX8IFz6jQ-7CW_RqeKKsw",
      "name": "ももたろう",
      "timeSec": 11580
    },
    {
      "channelId": "UCJeqXqAFicpGzWZbG0nVU6A",
      "name": "いかす",
      "timeSec": 25196
    },
    {
      "channelId": "UCEgzo1yNYRKm6HkuroYl4xw",
      "name": "おしるこポタージュ",
      "timeSec": 4672
    }
  ]
}
